__init__.py
censusapi/__init__.py
censusapi/censusgdf.py
censusapi/helperfunctions.py
example/example.py
geocensusapi-0.0.2.dist-info/METADATA
geocensusapi-0.0.2.dist-info/WHEEL
geocensusapi-0.0.2.dist-info/licenses/LICENSE
geocensusapi-0.0.2.dist-info/RECORD
