Metadata-Version: 2.1
Name: geocensusapi
Version: 0.0.2
Summary: A small example package
Project-URL: Homepage, https://github.com/zoedesimone/census-api
Project-URL: Bug Tracker, https://github.com/zoedesimone/census-api/issues
Author-email: Zoe De Simone <zoed@mit.edu>
License-File: LICENSE
Requires-Python: >=3.7
